{
  "scopes": [
    {
      "key": "read:pull-notifications",
      "name": "Read pull notifications",
      "description": "Read pull notifications"
    }
  ],
  "api": {
    "name": "Push Pull Notifications",
    "description": "This API allows notifications to be sent (pushed) to software developers or allows the software developer to get (pull) \nnotifications. Notifications are create by other HMRC services.",
    "context": "misc/push-pull-notification",
    "categories": [
      "OTHER"
    ],
    "versions": [
      {
        "version": "1.0",
        "status": "BETA",
        "endpointsEnabled": true,
        "access": {
          "type": "PRIVATE",
          "isTrial": true,
          "whitelistedApplicationIds": [
            "cfd9bf91-2a92-4ba4-b495-e44a505babb7",
            "ab349380-17cc-4de0-a7ac-c76baedd7133",
            "b5431e7f-3966-4aa5-aee5-65e5951d2f78"
          ]
        }
      }
    ]
  }
}